ngautonml_forecasting/__init__.py
ngautonml_forecasting/examples_test.py
ngautonml_forecasting/py.typed
ngautonml_forecasting/algorithms/__init__.py
ngautonml_forecasting/algorithms/neuralforecast/AutoNHITS.py
ngautonml_forecasting/algorithms/neuralforecast/AutoNHITS_test.py
ngautonml_forecasting/algorithms/neuralforecast/NBEATS.py
ngautonml_forecasting/algorithms/neuralforecast/NBEATS_test.py
ngautonml_forecasting/algorithms/neuralforecast/NBEATSx.py
ngautonml_forecasting/algorithms/neuralforecast/NBEATSx_test.py
ngautonml_forecasting/algorithms/neuralforecast/NHITS.py
ngautonml_forecasting/algorithms/neuralforecast/NHITS_test.py
ngautonml_forecasting/algorithms/neuralforecast/__init__.py
ngautonml_forecasting/algorithms/neuralforecast/neuralforecast_auto_model.py
ngautonml_forecasting/algorithms/neuralforecast/neuralforecast_model.py
ngautonml_forecasting/algorithms/neuralforecast/neuralforecast_model_test.py
ngautonml_forecasting/bugs/bug831_test.py
ngautonml_forecasting/config_components/__init__.py
ngautonml_forecasting/config_components/forecasting_config.py
ngautonml_forecasting/config_components/forecasting_config_test.py
ngautonml_forecasting/splitters/__init__.py
ngautonml_forecasting/splitters/forecasting_splitter.py
ngautonml_forecasting/splitters/forecasting_splitter_test.py
ngautonml_forecasting/templates/__init__.py
ngautonml_forecasting/templates/forecasting.py
ngautonml_forecasting/templates/forecasting_test.py
ngautonml_forecasting/templates/impl/template_auto_test.py
ngautonml_forecasting-0.5.0b8.dist-info/METADATA
ngautonml_forecasting-0.5.0b8.dist-info/WHEEL
ngautonml_forecasting-0.5.0b8.dist-info/entry_points.txt
ngautonml_forecasting-0.5.0b8.dist-info/top_level.txt
ngautonml_forecasting-0.5.0b8.dist-info/RECORD
