Metadata-Version: 2.3
Name: ngautonml_forecasting
Version: 0.5.0b8
Summary: a plugin that installs forecasting tools for ngAutonML
Keywords: machine learning,forecasting
Author: L.H. Piggy Yarroll
Author-email: piggy@cmu.edu
Classifier: Development Status :: 4 - Beta
Classifier: Intended Audience :: Science/Research
Classifier: Topic :: Scientific/Engineering :: Artificial Intelligence
Classifier: Typing :: Typed
